finpull_core/__init__.py
finpull_core/api.py
finpull_core/core/__init__.py
finpull_core/core/data_models.py
finpull_core/core/data_sources.py
finpull_core/core/scraper.py
finpull_core/core/storage.py
finpull_core/utils/__init__.py
finpull_core/utils/batch.py
finpull_core/utils/compatibility.py
finpull_core/utils/export.py
finpull_core-1.1.0.dist-info/METADATA
finpull_core-1.1.0.dist-info/WHEEL
finpull_core-1.1.0.dist-info/top_level.txt
finpull_core-1.1.0.dist-info/RECORD
